README.md
setup.py
jaxlob/__init__.py
jaxlob.egg-info/PKG-INFO
jaxlob.egg-info/SOURCES.txt
jaxlob.egg-info/dependency_links.txt
jaxlob.egg-info/top_level.txt
jaxlob/gymnax_exchange/__init__.py
jaxlob/gymnax_exchange/jaxen/__init__.py
jaxlob/gymnax_exchange/jaxen/arbi_env.py
jaxlob/gymnax_exchange/jaxen/base_env.py
jaxlob/gymnax_exchange/jaxen/exec_env.py
jaxlob/gymnax_exchange/jaxen/nexec_env.py
jaxlob/gymnax_exchange/jaxob/JaxOrderBookArrays.py
jaxlob/gymnax_exchange/jaxob/JaxOrderBookWrapper.py
jaxlob/gymnax_exchange/jaxob/__init__.py
jaxlob/gymnax_exchange/jaxob/jorderbook.py
jaxlob/gymnax_exchange/jaxrl/__init__.py
jaxlob/gymnax_exchange/jaxrl/onlySteps_noRL.py
jaxlob/gymnax_exchange/jaxrl/ppoRnnExecCont.py
jaxlob/gymnax_exchange/jaxrl/ppoS5ExecCont.py
jaxlob/gymnax_exchange/jaxrl/ppoS5ExecDisc.py
jaxlob/gymnax_exchange/test_scripts/__init__.py
jaxlob/gymnax_exchange/test_scripts/comparison.py
jaxlob/gymnax_exchange/test_scripts/comparisonS5ppo.py
jaxlob/gymnax_exchange/test_scripts/evaluation.py
jaxlob/gymnax_exchange/test_scripts/jaxob_test.py
jaxlob/gymnax_exchange/test_scripts/outSample.py
jaxlob/gymnax_exchange/test_scripts/outSampleS5ppo.py
jaxlob/gymnax_exchange/test_scripts/singleEnv.py
jaxlob/gymnax_exchange/test_scripts/testing_base_env.py
jaxlob/gymnax_exchange/test_scripts/testing_exec_env.py
jaxlob/gymnax_exchange/test_scripts/twap.py
jaxlob/gymnax_exchange/test_scripts/vmapEnv.py