Metadata-Version: 2.1
Name: jaxlob
Version: 0.19
Summary: UNKNOWN
License: UNKNOWN
Platform: UNKNOWN
